rageval/__init__.py
rageval/eval/__init__.py
rageval/eval/retrieval.py
rageval/generate/__init__.py
rageval/generate/load.py
rageval/generate/questions.py
rag_eval-0.1.3.dist-info/LICENSE
rag_eval-0.1.3.dist-info/METADATA
rag_eval-0.1.3.dist-info/WHEEL
rag_eval-0.1.3.dist-info/RECORD
